cape_dataframes/__init__.py
cape_dataframes/audit/__init__.py
cape_dataframes/audit/audit.py
cape_dataframes/coordinator/__init__.py
cape_dataframes/coordinator/client.py
cape_dataframes/coordinator/client_test.py
cape_dataframes/coordinator/auth/__init__.py
cape_dataframes/coordinator/auth/api_token.py
cape_dataframes/coordinator/auth/api_token_test.py
cape_dataframes/pandas/__init__.py
cape_dataframes/pandas/dtypes.py
cape_dataframes/pandas/registry.py
cape_dataframes/pandas/registry_test.py
cape_dataframes/pandas/transformer.py
cape_dataframes/pandas/transformations/__init__.py
cape_dataframes/pandas/transformations/base.py
cape_dataframes/pandas/transformations/column_redact.py
cape_dataframes/pandas/transformations/column_redact_test.py
cape_dataframes/pandas/transformations/perturbation.py
cape_dataframes/pandas/transformations/perturbation_test.py
cape_dataframes/pandas/transformations/rounding.py
cape_dataframes/pandas/transformations/rounding_test.py
cape_dataframes/pandas/transformations/row_redact.py
cape_dataframes/pandas/transformations/row_redact_test.py
cape_dataframes/pandas/transformations/test_utils.py
cape_dataframes/pandas/transformations/tokenizer.py
cape_dataframes/pandas/transformations/tokenizer_test.py
cape_dataframes/policy/__init__.py
cape_dataframes/policy/data.py
cape_dataframes/policy/data_test.py
cape_dataframes/policy/exceptions.py
cape_dataframes/policy/policy.py
cape_dataframes/policy/policy_test.py
cape_dataframes/policy/policy_test_fixtures.py
cape_dataframes/spark/__init__.py
cape_dataframes/spark/dtypes.py
cape_dataframes/spark/registry.py
cape_dataframes/spark/registry_test.py
cape_dataframes/spark/transformer.py
cape_dataframes/spark/utils.py
cape_dataframes/spark/transformations/__init__.py
cape_dataframes/spark/transformations/base.py
cape_dataframes/spark/transformations/perturbation.py
cape_dataframes/spark/transformations/perturbation_test.py
cape_dataframes/spark/transformations/redaction.py
cape_dataframes-0.3.1.dist-info/LICENSE
cape_dataframes-0.3.1.dist-info/METADATA
cape_dataframes-0.3.1.dist-info/NOTICE
cape_dataframes-0.3.1.dist-info/WHEEL
cape_dataframes-0.3.1.dist-info/top_level.txt
cape_dataframes-0.3.1.dist-info/RECORD
