Metadata-Version: 2.1
Name: cape-dataframes
Version: 0.3.1
Summary: Cape manages secure access to all of your data.
Home-page: https://github.com/capeprivacy/cape-dataframes
Author: Cape Privacy
Author-email: contact@capeprivacy.com
License: Apache License 2.0
Classifier: Programming Language :: Python :: 3
Classifier: License :: OSI Approved :: Apache Software License
Classifier: Development Status :: 3 - Alpha
Classifier: Operating System :: OS Independent
Classifier: Topic :: Scientific/Engineering :: Artificial Intelligence
Classifier: Topic :: Security :: Cryptography
Requires-Python: >=3.6
License-File: LICENSE
License-File: NOTICE
Requires-Dist: pandas
Requires-Dist: pycryptodome
Requires-Dist: pyyaml
Requires-Dist: requests
Requires-Dist: rfc3339
Provides-Extra: spark
Requires-Dist: pyspark (>=2.4) ; extra == 'spark'
Requires-Dist: pyarrow (>=0.15.1) ; extra == 'spark'
